README.md
setup.cfg
setup.py
nci_eval/__init__.py
nci_eval/metrics.py
nci_eval/plots.py
nci_eval.egg-info/PKG-INFO
nci_eval.egg-info/SOURCES.txt
nci_eval.egg-info/dependency_links.txt
nci_eval.egg-info/requires.txt
nci_eval.egg-info/top_level.txt
test/nci_eval/__init__.py
test/nci_eval/test_metrics.py